ssNMR/__init__.py
ssNMR/__main__.py
ssNMR/formatting.py
ssNMR_fitting-1.0.1.dist-info/LICENSE
ssNMR_fitting-1.0.1.dist-info/METADATA
ssNMR_fitting-1.0.1.dist-info/WHEEL
ssNMR_fitting-1.0.1.dist-info/top_level.txt
ssNMR_fitting-1.0.1.dist-info/RECORD
